ascii_guard/__init__.py
ascii_guard/cli.py
ascii_guard/config.py
ascii_guard/detector.py
ascii_guard/fixer.py
ascii_guard/linter.py
ascii_guard/models.py
ascii_guard/patterns.py
ascii_guard/py.typed
ascii_guard/scanner.py
ascii_guard/validator.py
ascii_guard-2.2.1.dist-info/licenses/LICENSE
ascii_guard-2.2.1.dist-info/METADATA
ascii_guard-2.2.1.dist-info/WHEEL
ascii_guard-2.2.1.dist-info/entry_points.txt
ascii_guard-2.2.1.dist-info/top_level.txt
ascii_guard-2.2.1.dist-info/RECORD
