Metadata-Version: 2.4
Name: ascii-guard
Version: 2.2.1
Summary: A minimal-dependency Python linter for detecting and fixing misaligned ASCII art boxes in documentation
Author-email: fxstein <fxstein@users.noreply.github.com>
License-Expression: Apache-2.0
Project-URL: Homepage, https://github.com/fxstein/ascii-guard
Project-URL: Repository, https://github.com/fxstein/ascii-guard
Project-URL: Issues, https://github.com/fxstein/ascii-guard/issues
Keywords: ascii,linter,documentation,ascii-art,box-drawing
Classifier: Development Status :: 5 - Production/Stable
Classifier: Intended Audience :: Developers
Classifier: Programming Language :: Python :: 3
Classifier: Programming Language :: Python :: 3.10
Classifier: Programming Language :: Python :: 3.11
Classifier: Programming Language :: Python :: 3.12
Classifier: Programming Language :: Python :: 3.13
Classifier: Programming Language :: Python :: 3.14
Classifier: Topic :: Software Development :: Quality Assurance
Classifier: Topic :: Text Processing
Requires-Python: >=3.10
License-File: LICENSE
Requires-Dist: tomli>=2.0.0; python_version < "3.11"
Provides-Extra: dev
Requires-Dist: pytest>=7.4.0; extra == "dev"
Requires-Dist: pytest-cov>=4.1.0; extra == "dev"
Requires-Dist: ruff>=0.1.0; extra == "dev"
Requires-Dist: mypy>=1.7.0; extra == "dev"
Requires-Dist: pre-commit>=3.5.0; extra == "dev"
Requires-Dist: build>=1.0.0; extra == "dev"
Requires-Dist: twine>=4.0.0; extra == "dev"
Dynamic: license-file
